[{"name": "Oklahoma City city, Oklahoma", "lat": 35.46708, "lng": -97.51366, "population": 681054}, {"name": "Tulsa city, Oklahoma", "lat": 36.12795, "lng": -95.90232, "population": 413066}, {"name": "Norman city, Oklahoma", "lat": 35.24057, "lng": -97.3453, "population": 128026}, {"name": "Broken Arrow city, Oklahoma", "lat": 36.03653, "lng": -95.781, "population": 113540}, {"name": "Edmond city, Oklahoma", "lat": 35.67381, "lng": -97.41308, "population": 94428}, {"name": "Lawton city, Oklahoma", "lat": 34.61922, "lng": -98.42111, "population": 90381}, {"name": "Moore city, Oklahoma", "lat": 35.3296, "lng": -97.475, "population": 62793}, {"name": "Midwest City city, Oklahoma", "lat": 35.45875, "lng": -97.37457, "population": 58409}, {"name": "Enid city, Oklahoma", "lat": 36.4067, "lng": -97.86986, "population": 51308}, {"name": "Stillwater city, Oklahoma", "lat": 36.1315, "lng": -97.07446, "population": 48394}, {"name": "Owasso city, Oklahoma", "lat": 36.28722, "lng": -95.83536, "population": 38240}, {"name": "Bartlesville city, Oklahoma", "lat": 36.73767, "lng": -95.94845, "population": 37290}, {"name": "Muskogee city, Oklahoma", "lat": 35.7438, "lng": -95.3564, "population": 36878}, {"name": "Shawnee city, Oklahoma", "lat": 35.37972, "lng": -96.92535, "population": 31377}, {"name": "Bixby city, Oklahoma", "lat": 35.94646, "lng": -95.87336, "population": 28609}, {"name": "Jenks city, Oklahoma", "lat": 35.99822, "lng": -95.9734, "population": 25949}, {"name": "Ardmore city, Oklahoma", "lat": 34.19651, "lng": -97.13185, "population": 24725}, {"name": "Ponca City city, Oklahoma", "lat": 36.72104, "lng": -97.06844, "population": 24424}, {"name": "Yukon city, Oklahoma", "lat": 35.51841, "lng": -97.76617, "population": 23630}, {"name": "Duncan city, Oklahoma", "lat": 34.48161, "lng": -97.96054, "population": 22692}, {"name": "Sapulpa city, Oklahoma", "lat": 36.00421, "lng": -96.12328, "population": 21929}, {"name": "Del City city, Oklahoma", "lat": 35.44828, "lng": -97.44079, "population": 21822}, {"name": "Bethany city, Oklahoma", "lat": 35.50717, "lng": -97.64173, "population": 20831}, {"name": "Mustang city, Oklahoma", "lat": 35.39185, "lng": -97.72514, "population": 19879}, {"name": "Sand Springs city, Oklahoma", "lat": 36.13648, "lng": -96.13197, "population": 19874}, {"name": "Claremore city, Oklahoma", "lat": 36.31509, "lng": -95.60945, "population": 19580}, {"name": "Altus city, Oklahoma", "lat": 34.65706, "lng": -99.30905, "population": 18729}, {"name": "Durant city, Oklahoma", "lat": 33.99515, "lng": -96.39254, "population": 18589}, {"name": "McAlester city, Oklahoma", "lat": 34.92613, "lng": -95.77362, "population": 18171}, {"name": "El Reno city, Oklahoma", "lat": 35.54183, "lng": -97.96127, "population": 16989}, {"name": "Ada city, Oklahoma", "lat": 34.76629, "lng": -96.6668, "population": 16481}, {"name": "Tahlequah city, Oklahoma", "lat": 35.9105, "lng": -94.97772, "population": 16209}, {"name": "Chickasha city, Oklahoma", "lat": 35.04054, "lng": -97.94717, "population": 16051}, {"name": "Glenpool city, Oklahoma", "lat": 35.94949, "lng": -96.00675, "population": 13691}, {"name": "Miami city, Oklahoma", "lat": 36.88772, "lng": -94.87089, "population": 12969}, {"name": "Guymon city, Oklahoma", "lat": 36.6901, "lng": -101.47705, "population": 12965}, {"name": "Choctaw city, Oklahoma", "lat": 35.48498, "lng": -97.26994, "population": 12182}, {"name": "Woodward city, Oklahoma", "lat": 36.42483, "lng": -99.40473, "population": 12133}, {"name": "Weatherford city, Oklahoma", "lat": 35.53877, "lng": -98.68555, "population": 12076}, {"name": "Elk City city, Oklahoma", "lat": 35.38961, "lng": -99.42875, "population": 11561}, {"name": "Okmulgee city, Oklahoma", "lat": 35.62516, "lng": -95.95403, "population": 11322}, {"name": "Newcastle city, Oklahoma", "lat": 35.2424, "lng": -97.59534, "population": 10984}, {"name": "Guthrie city, Oklahoma", "lat": 35.87651, "lng": -97.40866, "population": 10749}, {"name": "Warr Acres city, Oklahoma", "lat": 35.5261, "lng": -97.61811, "population": 10452}, {"name": "Coweta city, Oklahoma", "lat": 35.97182, "lng": -95.67101, "population": 9654}, {"name": "The Village city, Oklahoma", "lat": 35.57028, "lng": -97.5575, "population": 9538}, {"name": "Pryor Creek city, Oklahoma", "lat": 36.29966, "lng": -95.31127, "population": 9444}, {"name": "Blanchard city, Oklahoma", "lat": 35.15234, "lng": -97.66522, "population": 8879}, {"name": "Poteau city, Oklahoma", "lat": 35.06665, "lng": -94.61027, "population": 8807}, {"name": "Clinton city, Oklahoma", "lat": 35.5071, "lng": -98.9705, "population": 8521}, {"name": "Sallisaw city, Oklahoma", "lat": 35.46036, "lng": -94.80662, "population": 8510}, {"name": "Skiatook city, Oklahoma", "lat": 36.34654, "lng": -95.94536, "population": 8450}, {"name": "Cushing city, Oklahoma", "lat": 35.97968, "lng": -96.76175, "population": 8327}, {"name": "Collinsville city, Oklahoma", "lat": 36.36926, "lng": -95.86176, "population": 7881}, {"name": "Wagoner city, Oklahoma", "lat": 35.96569, "lng": -95.37771, "population": 7621}, {"name": "Catoosa city, Oklahoma", "lat": 36.18026, "lng": -95.77031, "population": 7440}, {"name": "Tuttle city, Oklahoma", "lat": 35.31388, "lng": -97.75361, "population": 7413}, {"name": "Piedmont city, Oklahoma", "lat": 35.67484, "lng": -97.75351, "population": 7402}, {"name": "Seminole city, Oklahoma", "lat": 35.23477, "lng": -96.64933, "population": 7146}, {"name": "Noble city, Oklahoma", "lat": 35.13492, "lng": -97.37109, "population": 6985}, {"name": "Idabel city, Oklahoma", "lat": 33.90741, "lng": -94.82217, "population": 6961}, {"name": "Grove city, Oklahoma", "lat": 36.59217, "lng": -94.79614, "population": 6956}, {"name": "Purcell city, Oklahoma", "lat": 35.02366, "lng": -97.37368, "population": 6651}, {"name": "Tecumseh city, Oklahoma", "lat": 35.26427, "lng": -96.93345, "population": 6302}, {"name": "Harrah city, Oklahoma", "lat": 35.48559, "lng": -97.18422, "population": 6245}, {"name": "Blackwell city, Oklahoma", "lat": 36.80147, "lng": -97.30014, "population": 6085}, {"name": "Pauls Valley city, Oklahoma", "lat": 34.71021, "lng": -97.22403, "population": 5992}, {"name": "Holdenville city, Oklahoma", "lat": 35.08348, "lng": -96.40135, "population": 5934}, {"name": "Anadarko city, Oklahoma", "lat": 35.0653, "lng": -98.24447, "population": 5745}, {"name": "Henryetta city, Oklahoma", "lat": 35.44165, "lng": -95.98642, "population": 5640}, {"name": "Verdigris town, Oklahoma", "lat": 36.25352, "lng": -95.66044, "population": 5256}, {"name": "Vinita city, Oklahoma", "lat": 36.64877, "lng": -95.161, "population": 5193}, {"name": "Hugo city, Oklahoma", "lat": 34.01158, "lng": -95.51218, "population": 5166}, {"name": "Sulphur city, Oklahoma", "lat": 34.51393, "lng": -96.96967, "population": 5065}, {"name": "Alva city, Oklahoma", "lat": 36.78957, "lng": -98.66488, "population": 5028}, {"name": "Lone Grove city, Oklahoma", "lat": 34.18097, "lng": -97.25331, "population": 4993}, {"name": "Hinton town, Oklahoma", "lat": 35.49323, "lng": -98.35472, "population": 4917}, {"name": "Kingfisher city, Oklahoma", "lat": 35.84473, "lng": -97.93931, "population": 4903}, {"name": "Sayre city, Oklahoma", "lat": 35.29565, "lng": -99.62824, "population": 4809}, {"name": "Perry city, Oklahoma", "lat": 36.28015, "lng": -97.30819, "population": 4484}, {"name": "Marlow city, Oklahoma", "lat": 34.63114, "lng": -97.95673, "population": 4385}, {"name": "McLoud city, Oklahoma", "lat": 35.41215, "lng": -97.10662, "population": 4351}, {"name": "Pocola town, Oklahoma", "lat": 35.25153, "lng": -94.46792, "population": 4255}, {"name": "Bristow city, Oklahoma", "lat": 35.83359, "lng": -96.3944, "population": 4248}, {"name": "Broken Bow city, Oklahoma", "lat": 34.02887, "lng": -94.74283, "population": 4228}, {"name": "Slaughterville town, Oklahoma", "lat": 35.09463, "lng": -97.28281, "population": 4163}, {"name": "Spencer city, Oklahoma", "lat": 35.51076, "lng": -97.37155, "population": 3978}, {"name": "Madill city, Oklahoma", "lat": 34.08708, "lng": -96.77466, "population": 3914}, {"name": "Nichols Hills city, Oklahoma", "lat": 35.54639, "lng": -97.54327, "population": 3870}, {"name": "Fort Gibson town, Oklahoma", "lat": 35.78218, "lng": -95.26014, "population": 3814}, {"name": "Stilwell city, Oklahoma", "lat": 35.81421, "lng": -94.6317, "population": 3700}, {"name": "Elgin city, Oklahoma", "lat": 34.78594, "lng": -98.29663, "population": 3656}, {"name": "Nowata city, Oklahoma", "lat": 36.69926, "lng": -95.63747, "population": 3517}, {"name": "Frederick city, Oklahoma", "lat": 34.34996, "lng": -98.988, "population": 3468}, {"name": "Hobart city, Oklahoma", "lat": 35.02458, "lng": -99.08756, "population": 3413}, {"name": "Dewey city, Oklahoma", "lat": 36.79128, "lng": -95.93276, "population": 3372}, {"name": "Hominy city, Oklahoma", "lat": 36.42193, "lng": -96.39303, "population": 3329}, {"name": "Roland town, Oklahoma", "lat": 35.41407, "lng": -94.51485, "population": 3316}, {"name": "Muldrow town, Oklahoma", "lat": 35.40342, "lng": -94.59752, "population": 3272}, {"name": "Mannford town, Oklahoma", "lat": 36.13286, "lng": -96.33043, "population": 3262}, {"name": "Perkins city, Oklahoma", "lat": 35.97976, "lng": -97.03129, "population": 3205}, {"name": "Cleveland city, Oklahoma", "lat": 36.31091, "lng": -96.47218, "population": 3205}, {"name": "Atoka city, Oklahoma", "lat": 34.38635, "lng": -96.1311, "population": 3195}, {"name": "Park Hill CDP, Oklahoma", "lat": 35.83444, "lng": -94.97208, "population": 3193}, {"name": "Wewoka city, Oklahoma", "lat": 35.14407, "lng": -96.49677, "population": 3133}, {"name": "Tishomingo city, Oklahoma", "lat": 34.23905, "lng": -96.68242, "population": 3101}, {"name": "Okemah city, Oklahoma", "lat": 35.42927, "lng": -96.30031, "population": 3074}, {"name": "Bethel Acres town, Oklahoma", "lat": 35.31137, "lng": -97.04506, "population": 3029}, {"name": "Checotah city, Oklahoma", "lat": 35.48244, "lng": -95.52282, "population": 3018}, {"name": "Tonkawa city, Oklahoma", "lat": 36.67059, "lng": -97.31503, "population": 3015}, {"name": "Heavener city, Oklahoma", "lat": 34.89196, "lng": -94.60779, "population": 2985}, {"name": "Pawhuska city, Oklahoma", "lat": 36.66906, "lng": -96.33122, "population": 2984}, {"name": "Cache city, Oklahoma", "lat": 34.62756, "lng": -98.61955, "population": 2930}, {"name": "Calera town, Oklahoma", "lat": 33.93042, "lng": -96.42954, "population": 2916}, {"name": "Jones town, Oklahoma", "lat": 35.56673, "lng": -97.28891, "population": 2885}, {"name": "Lindsay city, Oklahoma", "lat": 34.84049, "lng": -97.60985, "population": 2864}, {"name": "Chandler city, Oklahoma", "lat": 35.71278, "lng": -96.8362, "population": 2858}, {"name": "Davis city, Oklahoma", "lat": 34.42943, "lng": -97.17444, "population": 2823}, {"name": "New Cordell city, Oklahoma", "lat": 35.29686, "lng": -98.98377, "population": 2775}, {"name": "Eufaula city, Oklahoma", "lat": 35.29211, "lng": -95.58643, "population": 2766}, {"name": "Mangum city, Oklahoma", "lat": 34.87857, "lng": -99.50389, "population": 2762}, {"name": "Fairview city, Oklahoma", "lat": 36.27061, "lng": -98.47702, "population": 2740}, {"name": "Marietta city, Oklahoma", "lat": 33.93617, "lng": -97.12472, "population": 2719}, {"name": "Stroud city, Oklahoma", "lat": 35.76888, "lng": -96.65007, "population": 2719}, {"name": "Stigler city, Oklahoma", "lat": 35.25888, "lng": -95.11685, "population": 2703}, {"name": "Goldsby town, Oklahoma", "lat": 35.12391, "lng": -97.48662, "population": 2694}, {"name": "Watonga city, Oklahoma", "lat": 35.8475, "lng": -98.40273, "population": 2690}, {"name": "Longtown CDP, Oklahoma", "lat": 35.24237, "lng": -95.51859, "population": 2659}, {"name": "Turley CDP, Oklahoma", "lat": 36.24685, "lng": -95.96621, "population": 2607}, {"name": "Drumright city, Oklahoma", "lat": 35.98992, "lng": -96.59742, "population": 2560}, {"name": "Jay city, Oklahoma", "lat": 36.42711, "lng": -94.79557, "population": 2425}, {"name": "Walters city, Oklahoma", "lat": 34.35843, "lng": -98.35688, "population": 2412}, {"name": "Prague city, Oklahoma", "lat": 35.49533, "lng": -96.69523, "population": 2356}, {"name": "Healdton city, Oklahoma", "lat": 34.23374, "lng": -97.48687, "population": 2328}, {"name": "Nicoma Park city, Oklahoma", "lat": 35.49178, "lng": -97.32431, "population": 2313}, {"name": "Texanna CDP, Oklahoma", "lat": 35.35792, "lng": -95.51175, "population": 2293}, {"name": "Wilburton city, Oklahoma", "lat": 34.91845, "lng": -95.30402, "population": 2285}, {"name": "Commerce city, Oklahoma", "lat": 36.9349, "lng": -94.86147, "population": 2271}, {"name": "Oakhurst CDP, Oklahoma", "lat": 36.08061, "lng": -96.06236, "population": 2262}, {"name": "Antlers city, Oklahoma", "lat": 34.23376, "lng": -95.62327, "population": 2221}, {"name": "Kiefer town, Oklahoma", "lat": 35.94375, "lng": -96.05314, "population": 2187}, {"name": "Newkirk city, Oklahoma", "lat": 36.8818, "lng": -97.05529, "population": 2172}, {"name": "Hennessey town, Oklahoma", "lat": 36.10581, "lng": -97.89862, "population": 2151}, {"name": "Spiro town, Oklahoma", "lat": 35.24053, "lng": -94.62426, "population": 2102}, {"name": "Pink town, Oklahoma", "lat": 35.23269, "lng": -97.10003, "population": 2091}, {"name": "Krebs city, Oklahoma", "lat": 34.92978, "lng": -95.71864, "population": 2083}, {"name": "Chouteau town, Oklahoma", "lat": 36.18951, "lng": -95.3389, "population": 2059}, {"name": "Lexington city, Oklahoma", "lat": 35.01761, "lng": -97.33502, "population": 2010}, {"name": "Chelsea town, Oklahoma", "lat": 36.53204, "lng": -95.43457, "population": 1991}, {"name": "Burns Flat town, Oklahoma", "lat": 35.35469, "lng": -99.17502, "population": 1948}, {"name": "Hartshorne city, Oklahoma", "lat": 34.83879, "lng": -95.56192, "population": 1947}, {"name": "Pawnee city, Oklahoma", "lat": 36.35148, "lng": -96.8005, "population": 1936}, {"name": "Wynnewood city, Oklahoma", "lat": 34.64279, "lng": -97.16247, "population": 1927}, {"name": "Inola town, Oklahoma", "lat": 36.11315, "lng": -95.55156, "population": 1890}, {"name": "Waurika city, Oklahoma", "lat": 34.18375, "lng": -98.02629, "population": 1837}, {"name": "Arkoma town, Oklahoma", "lat": 35.33025, "lng": -94.44833, "population": 1806}, {"name": "Hooker city, Oklahoma", "lat": 36.86133, "lng": -101.21621, "population": 1802}, {"name": "Hollis city, Oklahoma", "lat": 34.68967, "lng": -99.91529, "population": 1795}, {"name": "Union City town, Oklahoma", "lat": 35.39952, "lng": -97.90671, "population": 1794}, {"name": "Norwood CDP, Oklahoma", "lat": 35.84468, "lng": -95.15123, "population": 1679}, {"name": "Coalgate city, Oklahoma", "lat": 34.53227, "lng": -96.2212, "population": 1667}, {"name": "Granite town, Oklahoma", "lat": 34.95115, "lng": -99.36838, "population": 1628}, {"name": "Haskell town, Oklahoma", "lat": 35.81897, "lng": -95.6804, "population": 1626}, {"name": "Langston town, Oklahoma", "lat": 35.93128, "lng": -97.27941, "population": 1619}, {"name": "Warner town, Oklahoma", "lat": 35.49169, "lng": -95.30894, "population": 1593}, {"name": "Helena town, Oklahoma", "lat": 36.54648, "lng": -98.27187, "population": 1537}, {"name": "Copeland CDP, Oklahoma", "lat": 36.66372, "lng": -94.82715, "population": 1511}, {"name": "Minco city, Oklahoma", "lat": 35.31562, "lng": -97.95141, "population": 1500}, {"name": "Luther town, Oklahoma", "lat": 35.66822, "lng": -97.19055, "population": 1492}, {"name": "Cherokee city, Oklahoma", "lat": 36.75068, "lng": -98.35773, "population": 1476}, {"name": "Latta CDP, Oklahoma", "lat": 34.75315, "lng": -96.7088, "population": 1465}, {"name": "Kingston town, Oklahoma", "lat": 34.00038, "lng": -96.7065, "population": 1431}, {"name": "Carnegie town, Oklahoma", "lat": 35.10274, "lng": -98.59959, "population": 1430}, {"name": "Justice CDP, Oklahoma", "lat": 36.2908, "lng": -95.56356, "population": 1424}, {"name": "McCord CDP, Oklahoma", "lat": 36.67312, "lng": -97.03592, "population": 1418}, {"name": "Stratford town, Oklahoma", "lat": 34.79531, "lng": -96.9605, "population": 1405}, {"name": "Wilson city, Oklahoma", "lat": 34.16866, "lng": -97.42541, "population": 1399}, {"name": "Byng town, Oklahoma", "lat": 34.86567, "lng": -96.66777, "population": 1393}, {"name": "Comanche city, Oklahoma", "lat": 34.3625, "lng": -97.97988, "population": 1378}, {"name": "Vian town, Oklahoma", "lat": 35.50425, "lng": -94.96983, "population": 1374}, {"name": "Locust Grove town, Oklahoma", "lat": 36.19816, "lng": -95.16887, "population": 1371}, {"name": "Westville town, Oklahoma", "lat": 35.99201, "lng": -94.57573, "population": 1364}, {"name": "Waukomis town, Oklahoma", "lat": 36.2861, "lng": -97.90273, "population": 1349}, {"name": "Dickson town, Oklahoma", "lat": 34.19022, "lng": -96.99875, "population": 1331}, {"name": "Grandview CDP, Oklahoma", "lat": 35.96476, "lng": -94.99866, "population": 1321}, {"name": "Oologah town, Oklahoma", "lat": 36.44378, "lng": -95.70891, "population": 1305}, {"name": "Snyder city, Oklahoma", "lat": 34.65507, "lng": -98.95345, "population": 1301}, {"name": "Morris city, Oklahoma", "lat": 35.60521, "lng": -95.86082, "population": 1299}, {"name": "Crescent city, Oklahoma", "lat": 35.95181, "lng": -97.5949, "population": 1299}, {"name": "Bushyhead CDP, Oklahoma", "lat": 36.46168, "lng": -95.50534, "population": 1292}, {"name": "Konawa city, Oklahoma", "lat": 34.95789, "lng": -96.75381, "population": 1288}, {"name": "Beaver town, Oklahoma", "lat": 36.81509, "lng": -100.52354, "population": 1280}, {"name": "Panama town, Oklahoma", "lat": 35.17118, "lng": -94.66843, "population": 1269}, {"name": "Shattuck town, Oklahoma", "lat": 36.26497, "lng": -99.87743, "population": 1249}, {"name": "Laverne town, Oklahoma", "lat": 36.70535, "lng": -99.89679, "population": 1223}, {"name": "Cleora CDP, Oklahoma", "lat": 36.59503, "lng": -94.94289, "population": 1220}, {"name": "Fletcher town, Oklahoma", "lat": 34.82362, "lng": -98.23415, "population": 1204}, {"name": "Whitehorn Cove CDP, Oklahoma", "lat": 35.99486, "lng": -95.28729, "population": 1201}, {"name": "Central High town, Oklahoma", "lat": 34.61433, "lng": -98.08865, "population": 1181}, {"name": "Beggs city, Oklahoma", "lat": 35.74139, "lng": -96.06646, "population": 1179}, {"name": "Mooreland town, Oklahoma", "lat": 36.4377, "lng": -99.20485, "population": 1178}, {"name": "Boise City city, Oklahoma", "lat": 36.73134, "lng": -102.50952, "population": 1166}, {"name": "Geronimo town, Oklahoma", "lat": 34.48313, "lng": -98.38765, "population": 1158}, {"name": "Thomas city, Oklahoma", "lat": 35.74519, "lng": -98.74512, "population": 1143}, {"name": "Okarche town, Oklahoma", "lat": 35.72487, "lng": -97.97567, "population": 1141}, {"name": "Fairfax town, Oklahoma", "lat": 36.57008, "lng": -96.70789, "population": 1136}, {"name": "Wetumka city, Oklahoma", "lat": 35.24188, "lng": -96.23677, "population": 1135}, {"name": "Sperry town, Oklahoma", "lat": 36.2977, "lng": -95.99565, "population": 1115}, {"name": "Fairland town, Oklahoma", "lat": 36.75139, "lng": -94.84726, "population": 1106}, {"name": "Boley town, Oklahoma", "lat": 35.48987, "lng": -96.47995, "population": 1091}, {"name": "Okeene town, Oklahoma", "lat": 36.11708, "lng": -98.31673, "population": 1090}, {"name": "Maysville town, Oklahoma", "lat": 34.86471, "lng": -97.37359, "population": 1087}, {"name": "Salina town, Oklahoma", "lat": 36.29163, "lng": -95.15542, "population": 1085}, {"name": "Yale city, Oklahoma", "lat": 36.11515, "lng": -96.70106, "population": 1059}, {"name": "Forest Park town, Oklahoma", "lat": 35.50959, "lng": -97.4469, "population": 1049}, {"name": "Buffalo town, Oklahoma", "lat": 36.82941, "lng": -99.63767, "population": 1039}, {"name": "Apache town, Oklahoma", "lat": 34.8936, "lng": -98.35861, "population": 1034}, {"name": "Barnsdall city, Oklahoma", "lat": 36.56094, "lng": -96.15577, "population": 1034}, {"name": "Wister town, Oklahoma", "lat": 34.96974, "lng": -94.72064, "population": 1031}, {"name": "Keys CDP, Oklahoma", "lat": 35.80279, "lng": -94.94136, "population": 1030}, {"name": "Briggs CDP, Oklahoma", "lat": 35.92176, "lng": -94.87852, "population": 1028}, {"name": "Colbert town, Oklahoma", "lat": 33.85836, "lng": -96.50763, "population": 1027}, {"name": "Wickliffe CDP, Oklahoma", "lat": 36.3121, "lng": -95.10738, "population": 1026}, {"name": "Kellyville town, Oklahoma", "lat": 35.969, "lng": -96.19392, "population": 1019}, {"name": "Caddo town, Oklahoma", "lat": 34.12561, "lng": -96.26364, "population": 1017}, {"name": "Meeker town, Oklahoma", "lat": 35.48931, "lng": -96.89765, "population": 1004}, {"name": "North Enid town, Oklahoma", "lat": 36.44584, "lng": -97.86339, "population": 1003}, {"name": "Erick city, Oklahoma", "lat": 35.21559, "lng": -99.86859, "population": 1000}, {"name": "West Siloam Springs town, Oklahoma", "lat": 36.17597, "lng": -94.59799, "population": 1000}, {"name": "Rush Springs town, Oklahoma", "lat": 34.77886, "lng": -97.95731, "population": 997}, {"name": "Geary city, Oklahoma", "lat": 35.63708, "lng": -98.31698, "population": 994}, {"name": "Shady Point town, Oklahoma", "lat": 35.12761, "lng": -94.66855, "population": 972}, {"name": "Bray town, Oklahoma", "lat": 34.60836, "lng": -97.81748, "population": 952}, {"name": "Goodwell town, Oklahoma", "lat": 36.59479, "lng": -101.62198, "population": 951}, {"name": "Gore town, Oklahoma", "lat": 35.54293, "lng": -95.11278, "population": 951}, {"name": "Rocky Point CDP, Oklahoma", "lat": 36.02561, "lng": -95.32208, "population": 946}, {"name": "Medford city, Oklahoma", "lat": 36.8034, "lng": -97.73784, "population": 932}, {"name": "Mounds town, Oklahoma", "lat": 35.87591, "lng": -96.06613, "population": 932}, {"name": "Hydro town, Oklahoma", "lat": 35.54813, "lng": -98.58011, "population": 927}, {"name": "Talihina town, Oklahoma", "lat": 34.75228, "lng": -95.04089, "population": 925}, {"name": "Grandfield city, Oklahoma", "lat": 34.23075, "lng": -98.68734, "population": 919}, {"name": "Toppers CDP, Oklahoma", "lat": 35.9662, "lng": -95.31968, "population": 911}, {"name": "Kenwood CDP, Oklahoma", "lat": 36.30124, "lng": -94.99787, "population": 904}, {"name": "Oilton city, Oklahoma", "lat": 36.08266, "lng": -96.58144, "population": 885}, {"name": "Pond Creek city, Oklahoma", "lat": 36.66784, "lng": -97.80239, "population": 885}, {"name": "Ringling town, Oklahoma", "lat": 34.17726, "lng": -97.59147, "population": 869}, {"name": "Maud city, Oklahoma", "lat": 35.13345, "lng": -96.77797, "population": 867}, {"name": "Dibble town, Oklahoma", "lat": 35.01965, "lng": -97.62708, "population": 867}, {"name": "Tipton town, Oklahoma", "lat": 34.49936, "lng": -99.13628, "population": 864}, {"name": "Quinton town, Oklahoma", "lat": 35.12606, "lng": -95.36648, "population": 863}, {"name": "Temple town, Oklahoma", "lat": 34.27212, "lng": -98.23457, "population": 862}, {"name": "Texhoma town, Oklahoma", "lat": 36.50541, "lng": -101.78739, "population": 856}, {"name": "Moodys CDP, Oklahoma", "lat": 36.03407, "lng": -94.95641, "population": 854}, {"name": "Sunray CDP, Oklahoma", "lat": 34.4093, "lng": -97.95422, "population": 853}, {"name": "Seiling city, Oklahoma", "lat": 36.14465, "lng": -98.92544, "population": 850}, {"name": "Cashion town, Oklahoma", "lat": 35.80091, "lng": -97.67574, "population": 850}, {"name": "Oakland town, Oklahoma", "lat": 34.09318, "lng": -96.80242, "population": 831}, {"name": "Pettit CDP, Oklahoma", "lat": 35.77368, "lng": -94.97676, "population": 829}, {"name": "Cyril town, Oklahoma", "lat": 34.89847, "lng": -98.20293, "population": 827}, {"name": "Cookson CDP, Oklahoma", "lat": 35.72127, "lng": -94.91549, "population": 826}, {"name": "Taylor Ferry CDP, Oklahoma", "lat": 35.93449, "lng": -95.30538, "population": 819}, {"name": "Valliant town, Oklahoma", "lat": 34.00754, "lng": -95.0849, "population": 819}, {"name": "Woodall CDP, Oklahoma", "lat": 35.82457, "lng": -95.08235, "population": 816}, {"name": "Burneyville CDP, Oklahoma", "lat": 33.89012, "lng": -97.2924, "population": 815}, {"name": "Quapaw town, Oklahoma", "lat": 36.94363, "lng": -94.77137, "population": 811}, {"name": "Brushy CDP, Oklahoma", "lat": 35.56165, "lng": -94.74752, "population": 811}, {"name": "Davenport town, Oklahoma", "lat": 35.70938, "lng": -96.76421, "population": 809}, {"name": "Weleetka town, Oklahoma", "lat": 35.34029, "lng": -96.13597, "population": 806}, {"name": "Allen town, Oklahoma", "lat": 34.87763, "lng": -96.41289, "population": 805}, {"name": "Limestone CDP, Oklahoma", "lat": 36.31434, "lng": -95.74773, "population": 804}, {"name": "Peggs CDP, Oklahoma", "lat": 36.06728, "lng": -95.0718, "population": 789}, {"name": "Welling CDP, Oklahoma", "lat": 35.88105, "lng": -94.87032, "population": 781}, {"name": "Ninnekah town, Oklahoma", "lat": 34.96401, "lng": -97.94471, "population": 775}, {"name": "Pickett CDP, Oklahoma", "lat": 34.77951, "lng": -96.77552, "population": 774}, {"name": "Cheyenne town, Oklahoma", "lat": 35.61092, "lng": -99.67637, "population": 771}, {"name": "Lost City CDP, Oklahoma", "lat": 36.00065, "lng": -95.12231, "population": 767}, {"name": "Sentinel town, Oklahoma", "lat": 35.15698, "lng": -99.17346, "population": 763}, {"name": "Dewar town, Oklahoma", "lat": 35.45792, "lng": -95.94913, "population": 763}, {"name": "Brent CDP, Oklahoma", "lat": 35.36622, "lng": -94.79247, "population": 760}, {"name": "Flint Creek CDP, Oklahoma", "lat": 36.17693, "lng": -94.74671, "population": 741}, {"name": "Mountain View town, Oklahoma", "lat": 35.09952, "lng": -98.74975, "population": 740}, {"name": "Elmore City town, Oklahoma", "lat": 34.62932, "lng": -97.39395, "population": 738}, {"name": "Afton town, Oklahoma", "lat": 36.69653, "lng": -94.95746, "population": 734}, {"name": "Keefton CDP, Oklahoma", "lat": 35.57851, "lng": -95.30631, "population": 732}, {"name": "Adair town, Oklahoma", "lat": 36.43641, "lng": -95.27344, "population": 732}, {"name": "Sequoyah CDP, Oklahoma", "lat": 36.37974, "lng": -95.59684, "population": 730}, {"name": "Tyrone town, Oklahoma", "lat": 36.95566, "lng": -101.068, "population": 729}, {"name": "Mannsville town, Oklahoma", "lat": 34.18312, "lng": -96.88885, "population": 728}, {"name": "Colcord town, Oklahoma", "lat": 36.26471, "lng": -94.69234, "population": 728}, {"name": "Blair town, Oklahoma", "lat": 34.78037, "lng": -99.33325, "population": 727}, {"name": "Garber city, Oklahoma", "lat": 36.43667, "lng": -97.58101, "population": 725}, {"name": "Morrison town, Oklahoma", "lat": 36.29173, "lng": -97.0348, "population": 723}, {"name": "Rock Island town, Oklahoma", "lat": 35.18492, "lng": -94.48261, "population": 717}, {"name": "Haileyville city, Oklahoma", "lat": 34.85415, "lng": -95.57863, "population": 716}, {"name": "Kansas town, Oklahoma", "lat": 36.20536, "lng": -94.78894, "population": 711}, {"name": "Copan town, Oklahoma", "lat": 36.90047, "lng": -95.92529, "population": 710}, {"name": "Waynoka city, Oklahoma", "lat": 36.58469, "lng": -98.87763, "population": 708}, {"name": "Cherry Tree CDP, Oklahoma", "lat": 35.74647, "lng": -94.64392, "population": 703}, {"name": "Empire City town, Oklahoma", "lat": 34.47761, "lng": -98.05944, "population": 703}, {"name": "Springer town, Oklahoma", "lat": 34.29562, "lng": -97.11745, "population": 685}, {"name": "South Coffeyville town, Oklahoma", "lat": 36.99209, "lng": -95.62184, "population": 683}, {"name": "Wellston town, Oklahoma", "lat": 35.6861, "lng": -97.06269, "population": 679}, {"name": "Washington town, Oklahoma", "lat": 35.05469, "lng": -97.49073, "population": 673}, {"name": "Sterling town, Oklahoma", "lat": 34.74939, "lng": -98.17251, "population": 668}, {"name": "Arapaho town, Oklahoma", "lat": 35.5778, "lng": -98.95934, "population": 668}, {"name": "Ryan town, Oklahoma", "lat": 34.02136, "lng": -97.95411, "population": 667}, {"name": "Valley Brook town, Oklahoma", "lat": 35.40267, "lng": -97.48142, "population": 665}, {"name": "Roff town, Oklahoma", "lat": 34.62893, "lng": -96.84147, "population": 632}, {"name": "Fairfield CDP, Oklahoma", "lat": 35.83751, "lng": -94.6082, "population": 626}, {"name": "Howe town, Oklahoma", "lat": 34.94957, "lng": -94.6403, "population": 625}, {"name": "Wayne town, Oklahoma", "lat": 34.91691, "lng": -97.31652, "population": 625}, {"name": "Cole town, Oklahoma", "lat": 35.09855, "lng": -97.56274, "population": 624}, {"name": "Savanna town, Oklahoma", "lat": 34.83708, "lng": -95.83356, "population": 623}, {"name": "Welch town, Oklahoma", "lat": 36.87441, "lng": -95.0944, "population": 622}, {"name": "Wright City town, Oklahoma", "lat": 34.06629, "lng": -95.00701, "population": 616}, {"name": "Vici town, Oklahoma", "lat": 36.14881, "lng": -99.29943, "population": 611}, {"name": "Langley town, Oklahoma", "lat": 36.48026, "lng": -95.05361, "population": 606}, {"name": "Porum town, Oklahoma", "lat": 35.35713, "lng": -95.26339, "population": 602}, {"name": "Kiowa town, Oklahoma", "lat": 34.72329, "lng": -95.9029, "population": 595}, {"name": "Earlsboro town, Oklahoma", "lat": 35.3292, "lng": -96.80293, "population": 594}, {"name": "Corn town, Oklahoma", "lat": 35.37905, "lng": -98.7817, "population": 592}, {"name": "Paoli town, Oklahoma", "lat": 34.82704, "lng": -97.26288, "population": 583}, {"name": "Boswell town, Oklahoma", "lat": 34.02762, "lng": -95.86849, "population": 579}, {"name": "Billings town, Oklahoma", "lat": 36.5376, "lng": -97.44175, "population": 578}, {"name": "Bokchito town, Oklahoma", "lat": 34.01543, "lng": -96.14158, "population": 574}, {"name": "Porter town, Oklahoma", "lat": 35.86841, "lng": -95.51595, "population": 561}, {"name": "Clayton town, Oklahoma", "lat": 34.58613, "lng": -95.35575, "population": 555}, {"name": "Velma town, Oklahoma", "lat": 34.45642, "lng": -97.66384, "population": 554}, {"name": "Chewey CDP, Oklahoma", "lat": 36.11249, "lng": -94.72573, "population": 548}, {"name": "Winchester town, Oklahoma", "lat": 35.79057, "lng": -95.99813, "population": 546}, {"name": "Carney town, Oklahoma", "lat": 35.80589, "lng": -97.01554, "population": 545}, {"name": "Lahoma town, Oklahoma", "lat": 36.38799, "lng": -98.09032, "population": 539}, {"name": "Red Oak town, Oklahoma", "lat": 34.95133, "lng": -95.07944, "population": 537}, {"name": "Redbird Smith CDP, Oklahoma", "lat": 35.56393, "lng": -95.02406, "population": 526}, {"name": "Ramona town, Oklahoma", "lat": 36.53574, "lng": -95.92783, "population": 524}, {"name": "White Eagle CDP, Oklahoma", "lat": 36.62675, "lng": -97.08123, "population": 520}, {"name": "Zeb CDP, Oklahoma", "lat": 35.79659, "lng": -95.05512, "population": 520}, {"name": "Shady Grove CDP (Cherokee County), Oklahoma", "lat": 35.94854, "lng": -95.09524, "population": 519}, {"name": "Fort Cobb town, Oklahoma", "lat": 35.11527, "lng": -98.44533, "population": 518}, {"name": "Lyons Switch CDP, Oklahoma", "lat": 35.78898, "lng": -94.68533, "population": 518}, {"name": "Verden town, Oklahoma", "lat": 35.08332, "lng": -98.08612, "population": 508}, {"name": "Okay town, Oklahoma", "lat": 35.86502, "lng": -95.30773, "population": 505}, {"name": "Remy CDP, Oklahoma", "lat": 35.46144, "lng": -94.49957, "population": 505}, {"name": "Glencoe town, Oklahoma", "lat": 36.23408, "lng": -96.93285, "population": 499}, {"name": "Arnett town, Oklahoma", "lat": 36.13449, "lng": -99.77271, "population": 495}, {"name": "Canute town, Oklahoma", "lat": 35.42197, "lng": -99.27793, "population": 494}, {"name": "Fort Towson town, Oklahoma", "lat": 34.0314, "lng": -95.27764, "population": 492}, {"name": "Cartwright CDP, Oklahoma", "lat": 33.85539, "lng": -96.55698, "population": 492}, {"name": "Wyandotte town, Oklahoma", "lat": 36.80714, "lng": -94.7293, "population": 488}, {"name": "Shady Grove CDP (McIntosh County), Oklahoma", "lat": 35.4685, "lng": -95.41146, "population": 487}, {"name": "Hulbert town, Oklahoma", "lat": 35.93165, "lng": -95.14553, "population": 483}, {"name": "Carlisle CDP, Oklahoma", "lat": 35.50688, "lng": -95.03222, "population": 483}, {"name": "Alex town, Oklahoma", "lat": 34.9228, "lng": -97.77633, "population": 482}, {"name": "Hammon town, Oklahoma", "lat": 35.63232, "lng": -99.38322, "population": 479}, {"name": "Covington town, Oklahoma", "lat": 36.30747, "lng": -97.58636, "population": 472}, {"name": "Ketchum town, Oklahoma", "lat": 36.5281, "lng": -95.01669, "population": 471}, {"name": "Rocky Mountain CDP, Oklahoma", "lat": 35.79029, "lng": -94.7713, "population": 471}, {"name": "Olustee town, Oklahoma", "lat": 34.54775, "lng": -99.42407, "population": 468}, {"name": "Canton town, Oklahoma", "lat": 36.05502, "lng": -98.5884, "population": 468}, {"name": "Ravia town, Oklahoma", "lat": 34.24123, "lng": -96.75683, "population": 464}, {"name": "Johnson town, Oklahoma", "lat": 35.41377, "lng": -96.84931, "population": 457}, {"name": "Drummond town, Oklahoma", "lat": 36.30172, "lng": -98.03578, "population": 455}, {"name": "Forgan town, Oklahoma", "lat": 36.90698, "lng": -100.53798, "population": 450}, {"name": "Westport town, Oklahoma", "lat": 36.19343, "lng": -96.33714, "population": 448}, {"name": "Calumet town, Oklahoma", "lat": 35.60139, "lng": -98.12479, "population": 443}, {"name": "Turpin CDP, Oklahoma", "lat": 36.87046, "lng": -100.8825, "population": 442}, {"name": "Little Ponderosa CDP, Oklahoma", "lat": 36.96119, "lng": -100.87814, "population": 438}, {"name": "Binger town, Oklahoma", "lat": 35.30972, "lng": -98.34294, "population": 438}, {"name": "Keota town, Oklahoma", "lat": 35.25739, "lng": -94.92231, "population": 437}, {"name": "Cement town, Oklahoma", "lat": 34.93621, "lng": -98.13628, "population": 436}, {"name": "Gage town, Oklahoma", "lat": 36.31813, "lng": -99.7576, "population": 433}, {"name": "Ochelata town, Oklahoma", "lat": 36.60269, "lng": -95.97506, "population": 427}, {"name": "Christie CDP, Oklahoma", "lat": 35.97604, "lng": -94.64695, "population": 427}, {"name": "Schulter town, Oklahoma", "lat": 35.51127, "lng": -95.95654, "population": 422}, {"name": "Bernice town, Oklahoma", "lat": 36.6234, "lng": -94.91348, "population": 422}, {"name": "Dill City town, Oklahoma", "lat": 35.28182, "lng": -99.13365, "population": 420}, {"name": "Paden town, Oklahoma", "lat": 35.50836, "lng": -96.56709, "population": 419}, {"name": "Stringtown town, Oklahoma", "lat": 34.4696, "lng": -96.05552, "population": 419}, {"name": "Leedey town, Oklahoma", "lat": 35.86842, "lng": -99.34492, "population": 415}, {"name": "Stonewall town, Oklahoma", "lat": 34.64982, "lng": -96.52683, "population": 414}, {"name": "Tushka town, Oklahoma", "lat": 34.31865, "lng": -96.16733, "population": 413}, {"name": "Amber town, Oklahoma", "lat": 35.16023, "lng": -97.88205, "population": 413}, {"name": "Medicine Park town, Oklahoma", "lat": 34.73199, "lng": -98.48897, "population": 411}, {"name": "Depew town, Oklahoma", "lat": 35.80144, "lng": -96.51107, "population": 411}, {"name": "Long CDP, Oklahoma", "lat": 35.49782, "lng": -94.53886, "population": 408}, {"name": "Akins CDP, Oklahoma", "lat": 35.50397, "lng": -94.66679, "population": 405}, {"name": "Cedar Valley city, Oklahoma", "lat": 35.87292, "lng": -97.5005, "population": 405}, {"name": "Cedar Lake CDP, Oklahoma", "lat": 35.427, "lng": -98.19301, "population": 404}, {"name": "Eagletown CDP, Oklahoma", "lat": 34.04187, "lng": -94.57024, "population": 404}, {"name": "Ringwood town, Oklahoma", "lat": 36.38358, "lng": -98.23996, "population": 401}, {"name": "New Eucha CDP, Oklahoma", "lat": 36.39116, "lng": -94.85224, "population": 400}, {"name": "Thackerville town, Oklahoma", "lat": 33.78753, "lng": -97.13918, "population": 400}, {"name": "Chattanooga town, Oklahoma", "lat": 34.42386, "lng": -98.65402, "population": 400}, {"name": "Dover town, Oklahoma", "lat": 35.98135, "lng": -97.91082, "population": 400}, {"name": "Achille town, Oklahoma", "lat": 33.83462, "lng": -96.39017, "population": 398}, {"name": "Bokoshe town, Oklahoma", "lat": 35.19037, "lng": -94.79041, "population": 396}, {"name": "East Duke town, Oklahoma", "lat": 34.66283, "lng": -99.56963, "population": 394}, {"name": "Tenkiller CDP, Oklahoma", "lat": 35.80253, "lng": -94.85231, "population": 390}, {"name": "Wapanucka town, Oklahoma", "lat": 34.37347, "lng": -96.42513, "population": 386}, {"name": "Silo town, Oklahoma", "lat": 34.03574, "lng": -96.47447, "population": 384}, {"name": "Caney CDP, Oklahoma", "lat": 35.82956, "lng": -94.84003, "population": 382}, {"name": "Evening Shade CDP, Oklahoma", "lat": 35.62097, "lng": -94.90537, "population": 378}, {"name": "Tryon town, Oklahoma", "lat": 35.87705, "lng": -96.96959, "population": 378}, {"name": "Gregory CDP, Oklahoma", "lat": 36.16972, "lng": -95.57409, "population": 377}, {"name": "Prue town, Oklahoma", "lat": 36.24942, "lng": -96.26652, "population": 374}, {"name": "Lone Wolf town, Oklahoma", "lat": 34.99043, "lng": -99.2456, "population": 373}, {"name": "Peavine CDP, Oklahoma", "lat": 35.90032, "lng": -94.60663, "population": 372}, {"name": "Whitefield town, Oklahoma", "lat": 35.25429, "lng": -95.24483, "population": 371}, {"name": "Wynona town, Oklahoma", "lat": 36.54579, "lng": -96.32635, "population": 370}, {"name": "Asher town, Oklahoma", "lat": 34.98837, "lng": -96.9254, "population": 370}, {"name": "Foyil town, Oklahoma", "lat": 36.4306, "lng": -95.52192, "population": 368}, {"name": "Custer City town, Oklahoma", "lat": 35.66383, "lng": -98.88695, "population": 367}, {"name": "Carmen town, Oklahoma", "lat": 36.57912, "lng": -98.4579, "population": 360}, {"name": "Bowlegs town, Oklahoma", "lat": 35.14728, "lng": -96.66927, "population": 357}, {"name": "McCurtain town, Oklahoma", "lat": 35.15056, "lng": -94.96718, "population": 355}, {"name": "Spavinaw town, Oklahoma", "lat": 36.39393, "lng": -95.05018, "population": 350}, {"name": "Coyle town, Oklahoma", "lat": 35.95811, "lng": -97.23969, "population": 350}, {"name": "Eldon CDP, Oklahoma", "lat": 35.94013, "lng": -94.80919, "population": 347}, {"name": "Ripley town, Oklahoma", "lat": 36.01584, "lng": -96.90384, "population": 346}, {"name": "Oktaha town, Oklahoma", "lat": 35.57749, "lng": -95.47789, "population": 343}, {"name": "Sawyer town, Oklahoma", "lat": 34.01871, "lng": -95.37847, "population": 340}, {"name": "Sand Hill CDP, Oklahoma", "lat": 35.63426, "lng": -95.2012, "population": 339}, {"name": "Optima town, Oklahoma", "lat": 36.76127, "lng": -101.3492, "population": 338}, {"name": "Webbers Falls town, Oklahoma", "lat": 35.517, "lng": -95.16422, "population": 338}, {"name": "Tribbey town, Oklahoma", "lat": 35.10379, "lng": -97.1056, "population": 337}, {"name": "Bridge Creek town, Oklahoma", "lat": 35.23355, "lng": -97.73469, "population": 336}, {"name": "Fort Coffee town, Oklahoma", "lat": 35.29421, "lng": -94.57135, "population": 335}, {"name": "Vera town, Oklahoma", "lat": 36.45264, "lng": -95.89291, "population": 334}, {"name": "Katie town, Oklahoma", "lat": 34.59071, "lng": -97.32562, "population": 332}, {"name": "Shidler city, Oklahoma", "lat": 36.78052, "lng": -96.65995, "population": 328}, {"name": "Twin Oaks CDP, Oklahoma", "lat": 36.19743, "lng": -94.83785, "population": 328}, {"name": "Tupelo city, Oklahoma", "lat": 34.60269, "lng": -96.42079, "population": 327}, {"name": "Dustin town, Oklahoma", "lat": 35.27125, "lng": -96.02783, "population": 327}, {"name": "Kaw City city, Oklahoma", "lat": 36.76675, "lng": -96.86178, "population": 325}, {"name": "Cameron town, Oklahoma", "lat": 35.13746, "lng": -94.53929, "population": 323}, {"name": "Pin Oak Acres CDP, Oklahoma", "lat": 36.12256, "lng": -95.28886, "population": 321}, {"name": "Mountain Park town, Oklahoma", "lat": 34.69883, "lng": -98.95235, "population": 320}, {"name": "Cloud Creek CDP, Oklahoma", "lat": 36.29378, "lng": -94.75435, "population": 319}, {"name": "Fanshawe town, Oklahoma", "lat": 34.96195, "lng": -94.91118, "population": 317}, {"name": "Fort Supply town, Oklahoma", "lat": 36.57209, "lng": -99.57352, "population": 317}, {"name": "Sportsmen Acres town, Oklahoma", "lat": 36.24558, "lng": -95.25169, "population": 317}, {"name": "Eldorado town, Oklahoma", "lat": 34.47295, "lng": -99.64962, "population": 317}, {"name": "Cumberland CDP, Oklahoma", "lat": 34.05872, "lng": -96.59244, "population": 315}, {"name": "Fargo town, Oklahoma", "lat": 36.37421, "lng": -99.62216, "population": 312}, {"name": "Wakita town, Oklahoma", "lat": 36.88186, "lng": -97.92395, "population": 311}, {"name": "Agra town, Oklahoma", "lat": 35.89494, "lng": -96.87019, "population": 311}, {"name": "Old Green CDP, Oklahoma", "lat": 35.98533, "lng": -94.60823, "population": 310}, {"name": "Tonkawa Tribal Housing CDP, Oklahoma", "lat": 36.66974, "lng": -97.26625, "population": 310}, {"name": "Calvin town, Oklahoma", "lat": 34.96638, "lng": -96.24989, "population": 309}, {"name": "Wauhillau CDP, Oklahoma", "lat": 35.86101, "lng": -94.75947, "population": 307}, {"name": "Crowder town, Oklahoma", "lat": 35.11825, "lng": -95.67779, "population": 306}, {"name": "Barber CDP, Oklahoma", "lat": 35.75214, "lng": -94.84845, "population": 303}, {"name": "Notchietown CDP, Oklahoma", "lat": 35.58543, "lng": -95.08947, "population": 302}, {"name": "Lamont town, Oklahoma", "lat": 36.69132, "lng": -97.55827, "population": 301}, {"name": "Avant town, Oklahoma", "lat": 36.49067, "lng": -96.04412, "population": 301}, {"name": "Lane CDP, Oklahoma", "lat": 34.29988, "lng": -95.98963, "population": 300}, {"name": "Belfonte CDP, Oklahoma", "lat": 35.54292, "lng": -94.55117, "population": 298}, {"name": "Mill Creek town, Oklahoma", "lat": 34.40255, "lng": -96.8252, "population": 293}, {"name": "Eakly town, Oklahoma", "lat": 35.30536, "lng": -98.55619, "population": 293}, {"name": "Steely Hollow CDP, Oklahoma", "lat": 35.99169, "lng": -94.93595, "population": 292}, {"name": "Haworth town, Oklahoma", "lat": 33.8409, "lng": -94.65703, "population": 291}, {"name": "Arpelar CDP, Oklahoma", "lat": 34.93285, "lng": -95.9517, "population": 291}, {"name": "North Miami town, Oklahoma", "lat": 36.92013, "lng": -94.87965, "population": 290}, {"name": "Short CDP, Oklahoma", "lat": 35.5682, "lng": -94.49537, "population": 290}, {"name": "Coleman CDP, Oklahoma", "lat": 34.26465, "lng": -96.42063, "population": 290}, {"name": "Randlett town, Oklahoma", "lat": 34.17735, "lng": -98.46392, "population": 289}, {"name": "Taloga town, Oklahoma", "lat": 36.04024, "lng": -98.96404, "population": 288}, {"name": "Cleo Springs town, Oklahoma", "lat": 36.40467, "lng": -98.44011, "population": 287}, {"name": "Lowrey CDP, Oklahoma", "lat": 36.09995, "lng": -94.93091, "population": 286}, {"name": "Nicut CDP, Oklahoma", "lat": 35.60238, "lng": -94.56291, "population": 286}, {"name": "Kinta town, Oklahoma", "lat": 35.11976, "lng": -95.23824, "population": 285}, {"name": "Rocky Ford CDP, Oklahoma", "lat": 36.15577, "lng": -94.91102, "population": 283}, {"name": "Bennington town, Oklahoma", "lat": 34.00384, "lng": -96.03759, "population": 282}, {"name": "Jennings town, Oklahoma", "lat": 36.18228, "lng": -96.56916, "population": 280}, {"name": "Mallard Bay CDP, Oklahoma", "lat": 35.86225, "lng": -95.26385, "population": 280}, {"name": "Terral town, Oklahoma", "lat": 33.89663, "lng": -97.93823, "population": 280}, {"name": "Gracemont town, Oklahoma", "lat": 35.18786, "lng": -98.25911, "population": 279}, {"name": "Wanette town, Oklahoma", "lat": 34.96261, "lng": -97.03171, "population": 279}, {"name": "Keyes town, Oklahoma", "lat": 36.80763, "lng": -102.25173, "population": 276}, {"name": "Rattan town, Oklahoma", "lat": 34.19604, "lng": -95.40454, "population": 276}, {"name": "Cedar Crest CDP, Oklahoma", "lat": 36.12318, "lng": -95.17315, "population": 276}, {"name": "Indiahoma town, Oklahoma", "lat": 34.61989, "lng": -98.75205, "population": 275}, {"name": "Lehigh city, Oklahoma", "lat": 34.47473, "lng": -96.22169, "population": 272}, {"name": "Lenapah town, Oklahoma", "lat": 36.85135, "lng": -95.6357, "population": 272}, {"name": "Braggs town, Oklahoma", "lat": 35.66329, "lng": -95.19834, "population": 270}, {"name": "Oaks town, Oklahoma", "lat": 36.1698, "lng": -94.85293, "population": 267}, {"name": "Delaware town, Oklahoma", "lat": 36.77896, "lng": -95.64254, "population": 267}, {"name": "Ralston town, Oklahoma", "lat": 36.50348, "lng": -96.73738, "population": 266}, {"name": "Leonard CDP, Oklahoma", "lat": 35.92279, "lng": -95.80101, "population": 262}, {"name": "Edgewater Park CDP, Oklahoma", "lat": 34.82473, "lng": -98.3752, "population": 262}, {"name": "Simms CDP, Oklahoma", "lat": 35.39871, "lng": -95.16471, "population": 261}, {"name": "Titanic CDP, Oklahoma", "lat": 35.8907, "lng": -94.74064, "population": 259}, {"name": "Talala town, Oklahoma", "lat": 36.5295, "lng": -95.70107, "population": 258}, {"name": "Snake Creek CDP, Oklahoma", "lat": 36.17856, "lng": -95.09371, "population": 255}, {"name": "Roosevelt town, Oklahoma", "lat": 34.84828, "lng": -99.02233, "population": 254}, {"name": "Milburn town, Oklahoma", "lat": 34.23866, "lng": -96.55239, "population": 252}, {"name": "Gans town, Oklahoma", "lat": 35.38739, "lng": -94.69459, "population": 251}, {"name": "Goltry town, Oklahoma", "lat": 36.53189, "lng": -98.15096, "population": 251}, {"name": "Sand Point CDP, Oklahoma", "lat": 33.96015, "lng": -96.57105, "population": 251}, {"name": "Leach CDP, Oklahoma", "lat": 36.19785, "lng": -94.90986, "population": 249}, {"name": "Greasy CDP, Oklahoma", "lat": 35.68187, "lng": -94.70245, "population": 248}, {"name": "River Bottom CDP, Oklahoma", "lat": 35.63574, "lng": -95.23784, "population": 248}, {"name": "Kremlin town, Oklahoma", "lat": 36.54657, "lng": -97.83233, "population": 247}, {"name": "Foster town, Oklahoma", "lat": 34.60596, "lng": -97.48986, "population": 246}, {"name": "Red Rock town, Oklahoma", "lat": 36.46007, "lng": -97.17961, "population": 245}, {"name": "Francis town, Oklahoma", "lat": 34.87447, "lng": -96.5926, "population": 244}, {"name": "Gowen CDP, Oklahoma", "lat": 34.88328, "lng": -95.47238, "population": 244}, {"name": "Baron CDP, Oklahoma", "lat": 35.93553, "lng": -94.60203, "population": 243}, {"name": "Hochatown CDP, Oklahoma", "lat": 34.15074, "lng": -94.74249, "population": 242}, {"name": "Davidson town, Oklahoma", "lat": 34.2421, "lng": -99.07811, "population": 241}, {"name": "Sportmans Shores CDP, Oklahoma", "lat": 36.46401, "lng": -95.0829, "population": 239}, {"name": "Cromwell town, Oklahoma", "lat": 35.34074, "lng": -96.45957, "population": 238}, {"name": "Tiawah CDP, Oklahoma", "lat": 36.24829, "lng": -95.53619, "population": 235}, {"name": "Bluejacket town, Oklahoma", "lat": 36.80043, "lng": -95.07403, "population": 235}, {"name": "Canadian Shores CDP, Oklahoma", "lat": 35.17285, "lng": -95.74208, "population": 233}, {"name": "Dry Creek CDP, Oklahoma", "lat": 35.73879, "lng": -94.87333, "population": 233}, {"name": "Gideon CDP, Oklahoma", "lat": 35.99715, "lng": -95.02792, "population": 229}, {"name": "Mead town, Oklahoma", "lat": 33.99799, "lng": -96.51864, "population": 227}, {"name": "Watts town, Oklahoma", "lat": 36.10727, "lng": -94.57181, "population": 227}, {"name": "Rose CDP, Oklahoma", "lat": 36.21236, "lng": -95.03814, "population": 225}, {"name": "Soper town, Oklahoma", "lat": 34.03207, "lng": -95.6966, "population": 225}, {"name": "Lake Ellsworth Addition CDP, Oklahoma", "lat": 34.83683, "lng": -98.32133, "population": 223}, {"name": "Disney town, Oklahoma", "lat": 36.47414, "lng": -95.01784, "population": 222}, {"name": "Dennis CDP, Oklahoma", "lat": 36.54733, "lng": -94.87692, "population": 221}, {"name": "Alderson town, Oklahoma", "lat": 34.90062, "lng": -95.68957, "population": 220}, {"name": "Bug Tussle CDP, Oklahoma", "lat": 35.03331, "lng": -95.67559, "population": 220}, {"name": "Millerton town, Oklahoma", "lat": 33.98487, "lng": -95.02309, "population": 215}, {"name": "Chance CDP, Oklahoma", "lat": 36.0675, "lng": -94.64627, "population": 215}, {"name": "Liberty CDP, Oklahoma", "lat": 35.46086, "lng": -94.54575, "population": 214}, {"name": "Mulhall town, Oklahoma", "lat": 36.1121, "lng": -97.3428, "population": 212}, {"name": "Lebanon CDP, Oklahoma", "lat": 33.97174, "lng": -96.92384, "population": 210}, {"name": "Marshall town, Oklahoma", "lat": 36.14968, "lng": -97.62324, "population": 210}, {"name": "White Oak CDP, Oklahoma", "lat": 36.60914, "lng": -95.27545, "population": 208}, {"name": "Butler town, Oklahoma", "lat": 35.63645, "lng": -99.18638, "population": 208}, {"name": "Hardesty town, Oklahoma", "lat": 36.61478, "lng": -101.19366, "population": 205}, {"name": "Sparrowhawk CDP, Oklahoma", "lat": 35.97055, "lng": -94.89278, "population": 202}, {"name": "Blue CDP, Oklahoma", "lat": 33.98994, "lng": -96.23037, "population": 200}, {"name": "Breckenridge town, Oklahoma", "lat": 36.45724, "lng": -97.72546, "population": 199}, {"name": "Dougherty town, Oklahoma", "lat": 34.39981, "lng": -97.05148, "population": 199}, {"name": "Meno town, Oklahoma", "lat": 36.3882, "lng": -98.17793, "population": 198}, {"name": "Jet town, Oklahoma", "lat": 36.66653, "lng": -98.18165, "population": 197}, {"name": "Little Rock CDP, Oklahoma", "lat": 36.21495, "lng": -95.09123, "population": 197}, {"name": "Ames town, Oklahoma", "lat": 36.24696, "lng": -98.18614, "population": 193}, {"name": "Camargo town, Oklahoma", "lat": 36.0179, "lng": -99.28845, "population": 193}, {"name": "Ingalls CDP, Oklahoma", "lat": 36.10474, "lng": -96.87077, "population": 192}, {"name": "Nash town, Oklahoma", "lat": 36.66505, "lng": -98.05197, "population": 192}, {"name": "Stuart town, Oklahoma", "lat": 34.90106, "lng": -96.09943, "population": 192}, {"name": "Elm Grove CDP, Oklahoma", "lat": 35.79596, "lng": -94.56811, "population": 192}, {"name": "Oak Hill-Piney CDP, Oklahoma", "lat": 36.37869, "lng": -94.72656, "population": 191}, {"name": "Bell CDP, Oklahoma", "lat": 35.72972, "lng": -94.5679, "population": 191}, {"name": "Grant CDP, Oklahoma", "lat": 33.93649, "lng": -95.51787, "population": 190}, {"name": "Teresita CDP, Oklahoma", "lat": 36.12304, "lng": -94.98036, "population": 188}, {"name": "Lawtonka Acres CDP, Oklahoma", "lat": 34.7805, "lng": -98.5296, "population": 187}, {"name": "Longdale town, Oklahoma", "lat": 36.13379, "lng": -98.55118, "population": 186}, {"name": "Marble City town, Oklahoma", "lat": 35.58388, "lng": -94.8174, "population": 186}, {"name": "Briartown CDP, Oklahoma", "lat": 35.29732, "lng": -95.23861, "population": 185}, {"name": "Caney town, Oklahoma", "lat": 34.23576, "lng": -96.21717, "population": 185}, {"name": "Marland town, Oklahoma", "lat": 36.56099, "lng": -97.15277, "population": 184}, {"name": "Byars town, Oklahoma", "lat": 34.87197, "lng": -97.05422, "population": 184}, {"name": "Crescent Springs CDP, Oklahoma", "lat": 35.89765, "lng": -97.6028, "population": 184}, {"name": "Fitzhugh town, Oklahoma", "lat": 34.65816, "lng": -96.76654, "population": 183}, {"name": "Pocasset town, Oklahoma", "lat": 35.178, "lng": -97.95919, "population": 183}, {"name": "Carter town, Oklahoma", "lat": 35.21695, "lng": -99.50358, "population": 183}, {"name": "Bessie town, Oklahoma", "lat": 35.38542, "lng": -98.98918, "population": 182}, {"name": "Zena CDP, Oklahoma", "lat": 36.50838, "lng": -94.84813, "population": 181}, {"name": "Pittsburg town, Oklahoma", "lat": 34.71164, "lng": -95.85018, "population": 180}, {"name": "Proctor CDP, Oklahoma", "lat": 35.98036, "lng": -94.73627, "population": 180}, {"name": "Twin Lakes CDP, Oklahoma", "lat": 35.86849, "lng": -97.66504, "population": 178}, {"name": "Garvin town, Oklahoma", "lat": 33.95718, "lng": -94.931, "population": 177}, {"name": "Osage town, Oklahoma", "lat": 36.2957, "lng": -96.41721, "population": 177}, {"name": "Pumpkin Hollow CDP, Oklahoma", "lat": 36.00597, "lng": -94.84144, "population": 176}, {"name": "Stoney Point CDP, Oklahoma", "lat": 35.56471, "lng": -94.67622, "population": 176}, {"name": "Chester CDP, Oklahoma", "lat": 36.21568, "lng": -98.92134, "population": 176}, {"name": "Dale CDP, Oklahoma", "lat": 35.3842, "lng": -97.04337, "population": 175}, {"name": "Freedom town, Oklahoma", "lat": 36.76816, "lng": -99.11259, "population": 174}, {"name": "Gotebo town, Oklahoma", "lat": 35.07123, "lng": -98.87426, "population": 174}, {"name": "Taft town, Oklahoma", "lat": 35.76033, "lng": -95.54599, "population": 174}, {"name": "Big Cabin town, Oklahoma", "lat": 36.54226, "lng": -95.22199, "population": 174}, {"name": "Drowning Creek CDP, Oklahoma", "lat": 36.4778, "lng": -94.89425, "population": 174}, {"name": "Whitesboro CDP, Oklahoma", "lat": 34.7047, "lng": -94.8735, "population": 172}, {"name": "Manitou town, Oklahoma", "lat": 34.50724, "lng": -98.98101, "population": 171}, {"name": "Enterprise CDP, Oklahoma", "lat": 35.22483, "lng": -95.37688, "population": 170}, {"name": "Preston CDP, Oklahoma", "lat": 35.71137, "lng": -95.98889, "population": 169}, {"name": "Arcadia town, Oklahoma", "lat": 35.66549, "lng": -97.32551, "population": 169}, {"name": "Castle town, Oklahoma", "lat": 35.46811, "lng": -96.39155, "population": 169}, {"name": "Aline town, Oklahoma", "lat": 36.50967, "lng": -98.44867, "population": 168}, {"name": "Dixon CDP, Oklahoma", "lat": 35.161, "lng": -96.51844, "population": 168}, {"name": "Greenville CDP, Oklahoma", "lat": 34.0044, "lng": -97.12129, "population": 167}, {"name": "West Peavine CDP, Oklahoma", "lat": 35.91149, "lng": -94.65278, "population": 167}, {"name": "Monroe CDP, Oklahoma", "lat": 34.99372, "lng": -94.51554, "population": 164}, {"name": "Warwick town, Oklahoma", "lat": 35.69034, "lng": -97.00503, "population": 164}, {"name": "Lakeside Village CDP, Oklahoma", "lat": 34.79888, "lng": -98.3811, "population": 162}, {"name": "Martha town, Oklahoma", "lat": 34.72598, "lng": -99.38666, "population": 162}, {"name": "Boynton town, Oklahoma", "lat": 35.64941, "lng": -95.6541, "population": 161}, {"name": "Honey Hill CDP, Oklahoma", "lat": 35.76473, "lng": -94.57495, "population": 160}, {"name": "Pump Back CDP, Oklahoma", "lat": 36.26066, "lng": -95.12107, "population": 160}, {"name": "Woodlawn Park town, Oklahoma", "lat": 35.50963, "lng": -97.64987, "population": 160}, {"name": "Braman town, Oklahoma", "lat": 36.92364, "lng": -97.33581, "population": 160}, {"name": "Cayuga CDP, Oklahoma", "lat": 36.63739, "lng": -94.65173, "population": 160}, {"name": "Etowah town, Oklahoma", "lat": 35.12593, "lng": -97.1704, "population": 159}, {"name": "Platter CDP, Oklahoma", "lat": 33.90785, "lng": -96.53396, "population": 159}, {"name": "Duchess Landing CDP, Oklahoma", "lat": 35.39847, "lng": -95.41658, "population": 157}, {"name": "Ballou CDP, Oklahoma", "lat": 36.14213, "lng": -95.19983, "population": 155}, {"name": "Cimarron City town, Oklahoma", "lat": 35.88878, "lng": -97.60321, "population": 155}, {"name": "Gene Autry town, Oklahoma", "lat": 34.31444, "lng": -97.04217, "population": 154}, {"name": "Liberty town, Oklahoma", "lat": 35.85302, "lng": -95.98624, "population": 153}, {"name": "Box CDP, Oklahoma", "lat": 35.57002, "lng": -94.97276, "population": 153}, {"name": "Tamaha town, Oklahoma", "lat": 35.39819, "lng": -95.01419, "population": 152}, {"name": "Slick town, Oklahoma", "lat": 35.77876, "lng": -96.2648, "population": 151}, {"name": "Haywood CDP, Oklahoma", "lat": 34.89196, "lng": -95.95202, "population": 150}, {"name": "Le Flore town, Oklahoma", "lat": 34.89459, "lng": -94.97803, "population": 150}, {"name": "Spaulding town, Oklahoma", "lat": 35.01308, "lng": -96.44044, "population": 149}, {"name": "Indianola town, Oklahoma", "lat": 35.16337, "lng": -95.77593, "population": 148}, {"name": "Adams CDP, Oklahoma", "lat": 36.75458, "lng": -101.07516, "population": 148}, {"name": "Kenefic town, Oklahoma", "lat": 34.14995, "lng": -96.36441, "population": 147}, {"name": "Vanoss CDP, Oklahoma", "lat": 34.75782, "lng": -96.87121, "population": 146}, {"name": "Butler CDP, Oklahoma", "lat": 36.53872, "lng": -94.74057, "population": 146}, {"name": "Hunter town, Oklahoma", "lat": 36.56402, "lng": -97.66251, "population": 145}, {"name": "Hennepin CDP, Oklahoma", "lat": 34.51722, "lng": -97.34538, "population": 143}, {"name": "Canadian town, Oklahoma", "lat": 35.17396, "lng": -95.6494, "population": 143}, {"name": "Murphy CDP, Oklahoma", "lat": 36.1341, "lng": -95.24137, "population": 140}, {"name": "Pinhook Corner CDP, Oklahoma", "lat": 35.53315, "lng": -94.89168, "population": 139}, {"name": "Reydon town, Oklahoma", "lat": 35.64981, "lng": -99.92361, "population": 137}, {"name": "Little City CDP, Oklahoma", "lat": 34.08396, "lng": -96.61605, "population": 136}, {"name": "Bearden town, Oklahoma", "lat": 35.3643, "lng": -96.38859, "population": 135}, {"name": "Bee CDP, Oklahoma", "lat": 34.12459, "lng": -96.56877, "population": 135}, {"name": "Clarita CDP, Oklahoma", "lat": 34.48412, "lng": -96.44488, "population": 135}, {"name": "Sharon town, Oklahoma", "lat": 36.27549, "lng": -99.33813, "population": 133}, {"name": "Fairmont town, Oklahoma", "lat": 36.35601, "lng": -97.70546, "population": 132}, {"name": "Sams Corner CDP, Oklahoma", "lat": 36.19832, "lng": -95.21671, "population": 132}, {"name": "Welty CDP, Oklahoma", "lat": 35.62716, "lng": -96.41715, "population": 131}, {"name": "Orlando town, Oklahoma", "lat": 36.14836, "lng": -97.37484, "population": 130}, {"name": "Norge town, Oklahoma", "lat": 34.98878, "lng": -97.99405, "population": 129}, {"name": "McBride CDP, Oklahoma", "lat": 33.9345, "lng": -96.63636, "population": 128}, {"name": "Rocky town, Oklahoma", "lat": 35.15641, "lng": -99.05965, "population": 128}, {"name": "Grayson town, Oklahoma", "lat": 35.50539, "lng": -95.87162, "population": 127}, {"name": "Lequire CDP, Oklahoma", "lat": 35.11115, "lng": -95.11186, "population": 127}, {"name": "Kemp town, Oklahoma", "lat": 33.76957, "lng": -96.35444, "population": 126}, {"name": "Peoria town, Oklahoma", "lat": 36.91556, "lng": -94.66955, "population": 126}, {"name": "Burlington town, Oklahoma", "lat": 36.90021, "lng": -98.42341, "population": 124}, {"name": "Bromide town, Oklahoma", "lat": 34.4183, "lng": -96.49476, "population": 123}, {"name": "Burbank town, Oklahoma", "lat": 36.69608, "lng": -96.72811, "population": 123}, {"name": "Phillips town, Oklahoma", "lat": 34.50422, "lng": -96.22223, "population": 122}, {"name": "Sparks town, Oklahoma", "lat": 35.61091, "lng": -96.81852, "population": 122}, {"name": "Lawrence Creek town, Oklahoma", "lat": 36.0838, "lng": -96.42676, "population": 121}, {"name": "St. Louis town, Oklahoma", "lat": 35.08126, "lng": -96.85979, "population": 121}, {"name": "Caney Ridge CDP, Oklahoma", "lat": 35.76393, "lng": -94.88276, "population": 120}, {"name": "Willow town, Oklahoma", "lat": 35.05153, "lng": -99.5099, "population": 119}, {"name": "Lamar town, Oklahoma", "lat": 35.09421, "lng": -96.12482, "population": 118}, {"name": "Albany CDP, Oklahoma", "lat": 33.87452, "lng": -96.15524, "population": 118}, {"name": "Cottonwood CDP, Oklahoma", "lat": 34.5547, "lng": -96.20324, "population": 117}, {"name": "Faxon town, Oklahoma", "lat": 34.46026, "lng": -98.57937, "population": 114}, {"name": "Greenfield town, Oklahoma", "lat": 35.72905, "lng": -98.37748, "population": 114}, {"name": "Isabella CDP, Oklahoma", "lat": 36.23899, "lng": -98.3264, "population": 114}, {"name": "Armstrong town, Oklahoma", "lat": 34.05282, "lng": -96.34484, "population": 113}, {"name": "Colony town, Oklahoma", "lat": 35.34854, "lng": -98.67146, "population": 112}, {"name": "Tatums town, Oklahoma", "lat": 34.47756, "lng": -97.46458, "population": 111}, {"name": "Olive CDP, Oklahoma", "lat": 36.02382, "lng": -96.48154, "population": 110}, {"name": "Cornish town, Oklahoma", "lat": 34.16358, "lng": -97.59639, "population": 110}, {"name": "Cowlington town, Oklahoma", "lat": 35.30963, "lng": -94.78397, "population": 109}, {"name": "Dacoma town, Oklahoma", "lat": 36.65962, "lng": -98.56347, "population": 109}, {"name": "Summit town, Oklahoma", "lat": 35.66958, "lng": -95.42065, "population": 108}, {"name": "Council Hill town, Oklahoma", "lat": 35.55581, "lng": -95.65251, "population": 108}, {"name": "Hallett town, Oklahoma", "lat": 36.23185, "lng": -96.56786, "population": 105}, {"name": "Bache CDP, Oklahoma", "lat": 34.89427, "lng": -95.65052, "population": 105}, {"name": "Blanco CDP, Oklahoma", "lat": 34.75082, "lng": -95.77356, "population": 105}, {"name": "Hastings town, Oklahoma", "lat": 34.22432, "lng": -98.10875, "population": 104}, {"name": "Gould town, Oklahoma", "lat": 34.66914, "lng": -99.77365, "population": 103}, {"name": "Rentiesville town, Oklahoma", "lat": 35.53354, "lng": -95.4848, "population": 103}, {"name": "Hanna town, Oklahoma", "lat": 35.20209, "lng": -95.88924, "population": 102}, {"name": "Hitchcock town, Oklahoma", "lat": 35.96766, "lng": -98.3497, "population": 102}, {"name": "Sweetwater town, Oklahoma", "lat": 35.41502, "lng": -99.9203, "population": 102}, {"name": "Tuskahoma CDP, Oklahoma", "lat": 34.62973, "lng": -95.28261, "population": 102}, {"name": "Foss town, Oklahoma", "lat": 35.45, "lng": -99.17074, "population": 101}, {"name": "Pensacola town, Oklahoma", "lat": 36.45923, "lng": -95.12776, "population": 101}, {"name": "Piney CDP, Oklahoma", "lat": 35.89052, "lng": -94.55594, "population": 101}, {"name": "Loco town, Oklahoma", "lat": 34.32951, "lng": -97.68064, "population": 99}, {"name": "Middleberg CDP, Oklahoma", "lat": 35.10661, "lng": -97.73416, "population": 99}, {"name": "Bridgeport city, Oklahoma", "lat": 35.54762, "lng": -98.37748, "population": 97}, {"name": "Mulberry CDP, Oklahoma", "lat": 35.86869, "lng": -94.69945, "population": 96}, {"name": "Wann town, Oklahoma", "lat": 36.9147, "lng": -95.80472, "population": 95}, {"name": "Johnson Prairie CDP, Oklahoma", "lat": 36.0791, "lng": -94.97587, "population": 94}, {"name": "Carlton Landing town, Oklahoma", "lat": 35.21173, "lng": -95.55705, "population": 94}, {"name": "Wainwright town, Oklahoma", "lat": 35.61352, "lng": -95.56556, "population": 93}, {"name": "Devol town, Oklahoma", "lat": 34.1954, "lng": -98.58819, "population": 93}, {"name": "Fox CDP, Oklahoma", "lat": 34.35786, "lng": -97.495, "population": 92}, {"name": "Gerty town, Oklahoma", "lat": 34.83573, "lng": -96.28888, "population": 92}, {"name": "Horntown town, Oklahoma", "lat": 35.0836, "lng": -96.23759, "population": 92}, {"name": "Narcissa CDP, Oklahoma", "lat": 36.80103, "lng": -94.92787, "population": 92}, {"name": "Manchester town, Oklahoma", "lat": 36.99449, "lng": -98.0351, "population": 90}, {"name": "Nescatunga CDP, Oklahoma", "lat": 36.75429, "lng": -98.15605, "population": 90}, {"name": "Carrier town, Oklahoma", "lat": 36.47859, "lng": -98.0172, "population": 90}, {"name": "Erin Springs town, Oklahoma", "lat": 34.81067, "lng": -97.60527, "population": 89}, {"name": "New Alluwe town, Oklahoma", "lat": 36.6101, "lng": -95.48856, "population": 89}, {"name": "Redbird town, Oklahoma", "lat": 35.88713, "lng": -95.58725, "population": 89}, {"name": "Dodge CDP, Oklahoma", "lat": 36.57893, "lng": -94.63848, "population": 89}, {"name": "Dotyville CDP, Oklahoma", "lat": 36.8514, "lng": -94.90976, "population": 89}, {"name": "Flute Springs CDP, Oklahoma", "lat": 35.62673, "lng": -94.79998, "population": 87}, {"name": "Kendrick town, Oklahoma", "lat": 35.7853, "lng": -96.77551, "population": 87}, {"name": "Lake Aluma town, Oklahoma", "lat": 35.53147, "lng": -97.44742, "population": 87}, {"name": "Hickory town, Oklahoma", "lat": 34.55648, "lng": -96.85342, "population": 86}, {"name": "Kildare town, Oklahoma", "lat": 36.80836, "lng": -97.04998, "population": 86}, {"name": "Atwood town, Oklahoma", "lat": 34.95515, "lng": -96.33676, "population": 85}, {"name": "Tullahassee town, Oklahoma", "lat": 35.84486, "lng": -95.44224, "population": 83}, {"name": "Washita CDP, Oklahoma", "lat": 35.10441, "lng": -98.34134, "population": 83}, {"name": "Addington town, Oklahoma", "lat": 34.24309, "lng": -97.9661, "population": 83}, {"name": "Hoyt CDP, Oklahoma", "lat": 35.26485, "lng": -95.30115, "population": 82}, {"name": "Marietta CDP, Oklahoma", "lat": 35.84833, "lng": -94.65326, "population": 82}, {"name": "Hoffman town, Oklahoma", "lat": 35.48884, "lng": -95.84469, "population": 81}, {"name": "Pontotoc CDP, Oklahoma", "lat": 34.48884, "lng": -96.62902, "population": 81}, {"name": "Centrahoma city, Oklahoma", "lat": 34.6104, "lng": -96.34367, "population": 81}, {"name": "Etta CDP, Oklahoma", "lat": 35.83622, "lng": -94.90301, "population": 80}, {"name": "Grand Lake Towne town, Oklahoma", "lat": 36.50567, "lng": -95.02769, "population": 80}, {"name": "Sasakwa town, Oklahoma", "lat": 34.94676, "lng": -96.52533, "population": 80}, {"name": "White Water CDP, Oklahoma", "lat": 36.50169, "lng": -94.72889, "population": 79}, {"name": "Fittstown CDP, Oklahoma", "lat": 34.60903, "lng": -96.64054, "population": 78}, {"name": "Lookeba town, Oklahoma", "lat": 35.363, "lng": -98.36384, "population": 78}, {"name": "Bowring CDP, Oklahoma", "lat": 36.87874, "lng": -96.11975, "population": 78}, {"name": "Bradley town, Oklahoma", "lat": 34.87797, "lng": -97.70874, "population": 78}, {"name": "Deer Creek town, Oklahoma", "lat": 36.80668, "lng": -97.51948, "population": 78}, {"name": "Felt CDP, Oklahoma", "lat": 36.56337, "lng": -102.79479, "population": 77}, {"name": "Smithville town, Oklahoma", "lat": 34.47276, "lng": -94.64647, "population": 77}, {"name": "Terlton town, Oklahoma", "lat": 36.18762, "lng": -96.49182, "population": 77}, {"name": "Dwight Mission CDP, Oklahoma", "lat": 35.55797, "lng": -94.85053, "population": 76}, {"name": "Hillsdale town, Oklahoma", "lat": 36.56325, "lng": -97.99266, "population": 75}, {"name": "Whippoorwill CDP, Oklahoma", "lat": 36.91201, "lng": -96.12769, "population": 75}, {"name": "Headrick town, Oklahoma", "lat": 34.62689, "lng": -99.13734, "population": 74}, {"name": "Leon town, Oklahoma", "lat": 33.87734, "lng": -97.42908, "population": 74}, {"name": "Mazie CDP, Oklahoma", "lat": 36.14256, "lng": -95.33021, "population": 74}, {"name": "Milfay CDP, Oklahoma", "lat": 35.75095, "lng": -96.55917, "population": 74}, {"name": "Oakwood town, Oklahoma", "lat": 35.93162, "lng": -98.70309, "population": 74}, {"name": "Cave Spring CDP, Oklahoma", "lat": 35.72818, "lng": -94.75814, "population": 74}, {"name": "Fair Oaks town, Oklahoma", "lat": 36.1701, "lng": -95.70849, "population": 73}, {"name": "Panola CDP, Oklahoma", "lat": 34.92212, "lng": -95.20867, "population": 73}, {"name": "Paradise Hill town, Oklahoma", "lat": 35.60735, "lng": -95.07309, "population": 73}, {"name": "Golden CDP, Oklahoma", "lat": 34.03074, "lng": -94.90297, "population": 71}, {"name": "Loyal town, Oklahoma", "lat": 35.97277, "lng": -98.11815, "population": 71}, {"name": "Nelagoney CDP, Oklahoma", "lat": 36.62604, "lng": -96.2441, "population": 71}, {"name": "Sour John CDP, Oklahoma", "lat": 35.62058, "lng": -95.14328, "population": 71}, {"name": "Brooksville town, Oklahoma", "lat": 35.20967, "lng": -96.96113, "population": 71}, {"name": "Blackburn town, Oklahoma", "lat": 36.37331, "lng": -96.59655, "population": 70}, {"name": "Bunch CDP, Oklahoma", "lat": 35.69885, "lng": -94.74024, "population": 70}, {"name": "Adamson CDP, Oklahoma", "lat": 34.92478, "lng": -95.54758, "population": 69}, {"name": "Emet CDP, Oklahoma", "lat": 34.206, "lng": -96.53929, "population": 69}, {"name": "Lima town, Oklahoma", "lat": 35.17371, "lng": -96.59811, "population": 68}, {"name": "Reagan CDP, Oklahoma", "lat": 34.34406, "lng": -96.71337, "population": 67}, {"name": "Lucien CDP, Oklahoma", "lat": 36.27476, "lng": -97.45503, "population": 66}, {"name": "Maramec town, Oklahoma", "lat": 36.24189, "lng": -96.68051, "population": 66}, {"name": "Iron Post CDP, Oklahoma", "lat": 36.15582, "lng": -95.13525, "population": 65}, {"name": "Shamrock town, Oklahoma", "lat": 35.91066, "lng": -96.57769, "population": 65}, {"name": "Swink CDP, Oklahoma", "lat": 34.01727, "lng": -95.20179, "population": 65}, {"name": "Sycamore CDP, Oklahoma", "lat": 36.39901, "lng": -94.71495, "population": 65}, {"name": "Elmer town, Oklahoma", "lat": 34.4808, "lng": -99.3521, "population": 65}, {"name": "Ratliff City town, Oklahoma", "lat": 34.45244, "lng": -97.51735, "population": 64}, {"name": "Strang town, Oklahoma", "lat": 36.41226, "lng": -95.13474, "population": 64}, {"name": "Mutual town, Oklahoma", "lat": 36.23046, "lng": -99.16797, "population": 63}, {"name": "Badger Lee CDP, Oklahoma", "lat": 35.47373, "lng": -94.81898, "population": 63}, {"name": "Hodgen CDP, Oklahoma", "lat": 34.84044, "lng": -94.63389, "population": 62}, {"name": "Rosedale town, Oklahoma", "lat": 34.91887, "lng": -97.18507, "population": 62}, {"name": "Skedee town, Oklahoma", "lat": 36.38047, "lng": -96.70392, "population": 62}, {"name": "Hendrix town, Oklahoma", "lat": 33.77526, "lng": -96.40708, "population": 61}, {"name": "Bull Hollow CDP, Oklahoma", "lat": 36.30463, "lng": -94.90083, "population": 61}, {"name": "Gate town, Oklahoma", "lat": 36.85171, "lng": -100.05521, "population": 60}, {"name": "Hitchita town, Oklahoma", "lat": 35.51982, "lng": -95.75174, "population": 60}, {"name": "Moyers CDP, Oklahoma", "lat": 34.325, "lng": -95.65109, "population": 60}, {"name": "New Woodville town, Oklahoma", "lat": 33.96885, "lng": -96.65484, "population": 60}, {"name": "IXL town, Oklahoma", "lat": 35.52877, "lng": -96.38539, "population": 59}, {"name": "Connerville CDP, Oklahoma", "lat": 34.44207, "lng": -96.62968, "population": 59}, {"name": "Hanson CDP, Oklahoma", "lat": 35.43801, "lng": -94.69835, "population": 58}, {"name": "Webb City town, Oklahoma", "lat": 36.80831, "lng": -96.71331, "population": 58}, {"name": "Albion town, Oklahoma", "lat": 34.66214, "lng": -95.09937, "population": 58}, {"name": "Bison CDP, Oklahoma", "lat": 36.19595, "lng": -97.89791, "population": 56}, {"name": "Dripping Springs CDP, Oklahoma", "lat": 36.17088, "lng": -94.68517, "population": 54}, {"name": "Scipio CDP, Oklahoma", "lat": 35.0513, "lng": -95.95558, "population": 53}, {"name": "Wardville CDP, Oklahoma", "lat": 34.65465, "lng": -96.03089, "population": 53}, {"name": "Rosston town, Oklahoma", "lat": 36.8129, "lng": -99.93275, "population": 52}, {"name": "Indianola CDP, Oklahoma", "lat": 36.4445, "lng": -94.67467, "population": 51}, {"name": "Nashoba CDP, Oklahoma", "lat": 34.48073, "lng": -95.2103, "population": 51}, {"name": "Utica CDP, Oklahoma", "lat": 33.90661, "lng": -96.22173, "population": 51}, {"name": "Douglas town, Oklahoma", "lat": 36.26046, "lng": -97.6666, "population": 51}, {"name": "Smith Village town, Oklahoma", "lat": 35.45079, "lng": -97.45701, "population": 49}, {"name": "Blackgum CDP, Oklahoma", "lat": 35.61205, "lng": -94.99214, "population": 47}, {"name": "Yeager town, Oklahoma", "lat": 35.15681, "lng": -96.33999, "population": 45}, {"name": "Elohim City CDP, Oklahoma", "lat": 35.64146, "lng": -94.51047, "population": 45}, {"name": "Earl CDP, Oklahoma", "lat": 34.20336, "lng": -96.89209, "population": 44}, {"name": "Nardin CDP, Oklahoma", "lat": 36.80409, "lng": -97.44987, "population": 43}, {"name": "Texola town, Oklahoma", "lat": 35.22246, "lng": -99.99296, "population": 43}, {"name": "Pershing CDP, Oklahoma", "lat": 36.59012, "lng": -96.27313, "population": 42}, {"name": "Bentley CDP, Oklahoma", "lat": 34.21741, "lng": -96.07971, "population": 42}, {"name": "Homestead CDP, Oklahoma", "lat": 36.14997, "lng": -98.397, "population": 41}, {"name": "Clearview town, Oklahoma", "lat": 35.39825, "lng": -96.18696, "population": 41}, {"name": "Eagle City CDP, Oklahoma", "lat": 35.93383, "lng": -98.58997, "population": 40}, {"name": "Quay CDP, Oklahoma", "lat": 36.1607, "lng": -96.70827, "population": 39}, {"name": "Finley CDP, Oklahoma", "lat": 34.32735, "lng": -95.49767, "population": 38}, {"name": "Moffett town, Oklahoma", "lat": 35.40467, "lng": -94.45572, "population": 38}, {"name": "Peckham CDP, Oklahoma", "lat": 36.88665, "lng": -97.17806, "population": 38}, {"name": "Amorita town, Oklahoma", "lat": 36.92401, "lng": -98.29362, "population": 38}, {"name": "Baker CDP, Oklahoma", "lat": 36.87041, "lng": -101.01771, "population": 37}, {"name": "Byron town, Oklahoma", "lat": 36.90138, "lng": -98.29442, "population": 37}, {"name": "Hollister town, Oklahoma", "lat": 34.34094, "lng": -98.87113, "population": 35}, {"name": "Sumner CDP, Oklahoma", "lat": 36.3183, "lng": -97.11793, "population": 35}, {"name": "Ashland town, Oklahoma", "lat": 34.76557, "lng": -96.07087, "population": 35}, {"name": "Mehan CDP, Oklahoma", "lat": 36.04583, "lng": -96.94013, "population": 34}, {"name": "Deer Lick CDP, Oklahoma", "lat": 36.45947, "lng": -94.74681, "population": 34}, {"name": "Strong City town, Oklahoma", "lat": 35.66984, "lng": -99.60045, "population": 33}, {"name": "Fay CDP, Oklahoma", "lat": 35.81609, "lng": -98.65866, "population": 32}, {"name": "Watova CDP, Oklahoma", "lat": 36.61972, "lng": -95.66045, "population": 32}, {"name": "Grainola town, Oklahoma", "lat": 36.93793, "lng": -96.64877, "population": 31}, {"name": "Kenton CDP, Oklahoma", "lat": 36.90636, "lng": -102.96521, "population": 31}, {"name": "Putnam town, Oklahoma", "lat": 35.85591, "lng": -98.96822, "population": 30}, {"name": "Zion CDP, Oklahoma", "lat": 35.78781, "lng": -94.64248, "population": 30}, {"name": "May town, Oklahoma", "lat": 36.61671, "lng": -99.74864, "population": 29}, {"name": "Lovell CDP, Oklahoma", "lat": 36.05603, "lng": -97.63647, "population": 28}, {"name": "Quinlan CDP, Oklahoma", "lat": 36.45622, "lng": -99.04573, "population": 28}, {"name": "Capron town, Oklahoma", "lat": 36.89666, "lng": -98.57762, "population": 27}, {"name": "Seward CDP, Oklahoma", "lat": 35.79667, "lng": -97.48697, "population": 26}, {"name": "Friendship town, Oklahoma", "lat": 34.69783, "lng": -99.22869, "population": 23}, {"name": "Old Eucha CDP, Oklahoma", "lat": 36.35513, "lng": -94.93791, "population": 23}, {"name": "Hopeton CDP, Oklahoma", "lat": 36.68818, "lng": -98.66201, "population": 22}, {"name": "Macomb town, Oklahoma", "lat": 35.1479, "lng": -97.00865, "population": 22}, {"name": "Oak Grove town, Oklahoma", "lat": 36.20561, "lng": -96.33842, "population": 22}, {"name": "Sugden town, Oklahoma", "lat": 34.08253, "lng": -97.97884, "population": 22}, {"name": "Fallis town, Oklahoma", "lat": 35.7493, "lng": -97.11822, "population": 21}, {"name": "Durham CDP, Oklahoma", "lat": 35.84389, "lng": -99.92613, "population": 21}, {"name": "Hough CDP, Oklahoma", "lat": 36.87196, "lng": -101.57474, "population": 20}, {"name": "Valley Park town, Oklahoma", "lat": 36.2788, "lng": -95.73574, "population": 19}, {"name": "Bryant CDP, Oklahoma", "lat": 35.39229, "lng": -96.06234, "population": 19}, {"name": "Foraker town, Oklahoma", "lat": 36.87283, "lng": -96.56921, "population": 18}, {"name": "Stidham town, Oklahoma", "lat": 35.36864, "lng": -95.70075, "population": 17}, {"name": "Clarksville CDP, Oklahoma", "lat": 35.82408, "lng": -95.51408, "population": 17}, {"name": "Renfrow town, Oklahoma", "lat": 36.92484, "lng": -97.65705, "population": 15}, {"name": "Meridian town, Oklahoma", "lat": 35.84423, "lng": -97.24556, "population": 14}, {"name": "Brush Creek CDP, Oklahoma", "lat": 36.41647, "lng": -94.78388, "population": 14}, {"name": "Loveland town, Oklahoma", "lat": 34.30499, "lng": -98.77127, "population": 13}, {"name": "Selman CDP, Oklahoma", "lat": 36.80141, "lng": -99.48932, "population": 12}, {"name": "Tagg Flats CDP, Oklahoma", "lat": 36.33872, "lng": -94.90364, "population": 12}, {"name": "Avard CDP, Oklahoma", "lat": 36.69736, "lng": -98.78936, "population": 11}, {"name": "Jefferson town, Oklahoma", "lat": 36.72034, "lng": -97.7909, "population": 9}, {"name": "Knowles town, Oklahoma", "lat": 36.87289, "lng": -100.19242, "population": 6}, {"name": "Lotsee town, Oklahoma", "lat": 36.13343, "lng": -96.20909, "population": 6}, {"name": "Lambert town, Oklahoma", "lat": 36.68324, "lng": -98.42366, "population": 5}, {"name": "Cooperton town, Oklahoma", "lat": 34.86651, "lng": -98.87587, "population": 3}]